github_issue_exporter/__init__.py
github_issue_exporter/__main__.py
github_issue_exporter/cli/__init__.py
github_issue_exporter/cli/main.py
github_issue_exporter/core/__init__.py
github_issue_exporter/core/auth.py
github_issue_exporter/core/config.py
github_issue_exporter/core/export_engine.py
github_issue_exporter/core/filesystem.py
github_issue_exporter/core/github_client.py
github_issue_exporter/core/transformer.py
github_issue_exporter-0.1.0.dist-info/METADATA
github_issue_exporter-0.1.0.dist-info/WHEEL
github_issue_exporter-0.1.0.dist-info/entry_points.txt
github_issue_exporter-0.1.0.dist-info/RECORD
