Metadata-Version: 2.4
Name: github-issue-exporter
Version: 0.1.0
Summary: Export GitHub issues to individual JSON files with incremental updates and credential management
Project-URL: Homepage, https://github.com/Beep-Boop-Digital/github-issue-exporter
Project-URL: Repository, https://github.com/Beep-Boop-Digital/github-issue-exporter
Project-URL: Issues, https://github.com/Beep-Boop-Digital/github-issue-exporter/issues
Author-email: Adam McKay <adam@beepboop.digital>
Requires-Python: >=3.11
Requires-Dist: cryptography>=45.0.3
Requires-Dist: httpx>=0.28.1
Requires-Dist: pydantic>=2.11.5
Requires-Dist: rich>=14.0.0
Requires-Dist: typer>=0.16.0
